{
  "http": [ { "root": "public" }
          , { "path": "/board.js", "file": "lib/board.js" }
          , { "path": "/lib/socket.io.js", "file": "node_modules/socket.io/support/socket.io-client/socket.io.js" }
          , { "path": "/transporter/receiver.js", "file": "node_modules/transporter/lib/receiver.js" }
          ]
, "socket": { "events": { "kibitz": { "controller": "bughouse", "action": "kibitz" }
                        , "join": { "controller": "bughouse", "action": "join" }
                        , "move": { "controller": "bughouse", "action": "move" }
                        , "rotate": { "controller": "bughouse", "action": "rotate" }
                        }
            , "disconnect": {"controller": "bughouse", "action": "disconnect"}
            }
}
